{
    "elements" : [
        {
        "date": "28.02",
        "theme": "Решение задач на оттачивание навыков по использованию условной конструкции, циклов по условию и по счетчику"
    },
    {
        "date": "01.03",
        "theme": "Динамическое изменение положения и внешнего вида элементов страницы Часть 1"     
    },
    {
        "date": "04.03",
        "theme": "Динамическое изменение положения и внешнего вида элементов страницы Часть 2"     
    },
    {
        "date": "06.03",
        "theme": "Программирование модальных окон и слайдеров Часть 1"     
    },
    {
        "date": "11.03",
        "theme": "Программирование модальных окон и слайдеров Часть 2"     
    },
    {
        "date": "13.03",
        "theme": "Работа с формой через JavaScript"     
    }
    ]
}
