{
    "products" : [
        {
        "name": "Котик-космонавт",
        "url": "1.jpg",
        "price": 4999
        },
        {
        "name": "Котик-монах",
        "url": "2.jpg",
        "price": 5699
        },
        {
        "name": "Котик-палладин",
        "url": "3.jpg",
        "price": 4599
        },
        {
        "name": "Котик-космонавт",
        "url": "4.jpg",
        "price": 4999
        },
        {
        "name": "Космический котик",
        "url": "4.jpg",
        "price": 5999
        }
   ]
}